Metadata-Version: 2.4
Name: mcp-server-tat
Version: 0.1.5
Summary: mcp server for Tencent Cloud Automation Tools
Requires-Python: >=3.10
Requires-Dist: mcp>=1.0.0
Requires-Dist: tencentcloud-sdk-python-common
Requires-Dist: tencentcloud-sdk-python-tat
